[
  {
    "giftId": 5586,
    "giftName": "Hearts",
    "userId": "6622882558081286145",
    "nickname": "BinhNgo2026",
    "profilePicture": "https://p16-common-sign.tiktokcdn.com/tos-alisg-avt-0068/8dd6446357b6b0a2ffbbc1176980d828~tplv-tiktokx-cropcenter:100:100.webp?dr=14579&refresh_token=0d038618&x-expires=1777172400&x-signature=rMr0fkMfnjhf9HCzhLq8q8BA2NQ%3D&t=4d5b0474&ps=13740610&shp=a5d48078&shcp=fdd36af4&idc=my",
    "amount": 1,
    "diamonds": 199,
    "timestamp": "2026-04-24T03:11:15.585Z",
    "id": 1777000275585
  },
  {
    "giftId": 5655,
    "giftName": "Rose",
    "userId": "7621485239449388052",
    "nickname": "😜RÌNH💕RÌNH😜BẺ Á Á Á😜😜😜",
    "profilePicture": "https://p16-common-sign.tiktokcdn.com/tos-alisg-avt-0068/e4c04e06cb7d364d72685bf01725da6a~tplv-tiktokx-cropcenter:100:100.webp?dr=14579&refresh_token=5802ebb7&x-expires=1777172400&x-signature=Qygw1NQYh21FdLjolFcvfq2dgOE%3D&t=4d5b0474&ps=13740610&shp=a5d48078&shcp=fdd36af4&idc=my",
    "amount": 9,
    "diamonds": 1,
    "timestamp": "2026-04-24T03:12:46.719Z",
    "id": 1777000366719
  },
  {
    "giftId": 59286,
    "giftName": "SEA Shell",
    "userId": "7621485239449388052",
    "nickname": "😜RÌNH💕RÌNH😜BẺ Á Á Á😜😜😜",
    "profilePicture": "https://p16-common-sign.tiktokcdn.com/tos-alisg-avt-0068/e4c04e06cb7d364d72685bf01725da6a~tplv-tiktokx-cropcenter:100:100.webp?dr=14579&refresh_token=5802ebb7&x-expires=1777172400&x-signature=Qygw1NQYh21FdLjolFcvfq2dgOE%3D&t=4d5b0474&ps=13740610&shp=a5d48078&shcp=fdd36af4&idc=my",
    "amount": 1,
    "diamonds": 1,
    "timestamp": "2026-04-24T03:13:03.310Z",
    "id": 1777000383310
  }
]