[
  {
    "id": 1,
    "name": "Khu Câu Lệnh",
    "nameEn": "Command Area",
    "icon": "command",
    "color": "#ff6b9d",
    "position": {
      "x": 2,
      "y": 8
    },
    "size": {
      "w": 40,
      "h": 35
    },
    "gifts": [
      {
        "giftId": 5586,
        "title": "Comment 111 để thả tim"
      },
      {
        "giftId": 5269,
        "title": "Comment 222 để biến hình"
      }
    ]
  },
  {
    "id": 2,
    "name": "Khu Hiệu Ứng",
    "nameEn": "Effect Area",
    "icon": "effect",
    "color": "#a855f7",
    "position": {
      "x": 2,
      "y": 45
    },
    "size": {
      "w": 40,
      "h": 45
    },
    "gifts": [
      {
        "giftId": 37953,
        "title": "GIận dữ"
      },
      {
        "giftId": 5827,
        "title": "Trói"
      },
      {
        "giftId": 54724,
        "title": "Đến đây chủ tịch"
      }
    ]
  },
  {
    "id": 3,
    "name": "Khu Vũ Đạo",
    "nameEn": "Dance Area",
    "icon": "dance",
    "color": "#06b6d4",
    "position": {
      "x": 58,
      "y": 8
    },
    "size": {
      "w": 40,
      "h": 50
    },
    "gifts": [
      {
        "giftId": 19441,
        "title": "Nhảy"
      },
      {
        "giftId": 6064,
        "title": "Nhảy"
      }
    ]
  }
]